listdiff2/__init__.py
listdiff2/listdiff2.py
listdiff2-0.1.1.dist-info/LICENSE
listdiff2-0.1.1.dist-info/METADATA
listdiff2-0.1.1.dist-info/WHEEL
listdiff2-0.1.1.dist-info/top_level.txt
listdiff2-0.1.1.dist-info/RECORD
