Metadata-Version: 2.1
Name: listdiff2
Version: 0.1.1
Summary: A pure Python library for fast comparison of large structured data, using set operations instead of loops to calculate differences between lists of dictionaries, supporting deep comparison of dictionary objects
Author-email: Rocks Wang <rockswang@foxmail.com>
License: MIT
Project-URL: Homepage, https://github.com/rockswang/list_diff
Keywords: diff,difference,list,dictionary,comparison,data-analysis
Classifier: Development Status :: 4 - Beta
Classifier: Intended Audience :: Developers
Classifier: License :: OSI Approved :: MIT License
Classifier: Operating System :: OS Independent
Classifier: Programming Language :: Python :: 3
Classifier: Programming Language :: Python :: 3.8
Classifier: Programming Language :: Python :: 3.9
Classifier: Programming Language :: Python :: 3.10
Classifier: Programming Language :: Python :: 3.11
Classifier: Programming Language :: Python :: 3.12
Classifier: Topic :: Software Development :: Libraries :: Python Modules
Classifier: Topic :: Utilities
Requires-Python: >=3.8
License-File: LICENSE
